soft_collect/__init__.py
soft_collect/cas.py
soft_collect/check.py
soft_collect/collect.py
soft_collect/config.py
soft_collect/console.py
soft_collect/db/__init__.py
soft_collect/db/abstract.py
soft_collect/db/db2.py
soft_collect/db/oracle.py
soft_collect/db/postgres.py
soft_collect/db/sqlserver.py
soft_collect/models/objects.py
soft_collect/query.py
soft_collect/save/__init__.py
soft_collect/save/abstract.py
soft_collect/save/local.py
soft_collect/save/s3.py
soft_collect/templates/.NAME-secrets.toml
soft_collect/templates/NAME-settings.toml
soft_collect/templates/__init__.py
soft_collect/utils/__init__.py
soft_collect/utils/print.py
soft_collect-0.3.12.dist-info/entry_points.txt
soft_collect-0.3.12.dist-info/WHEEL
soft_collect-0.3.12.dist-info/METADATA
soft_collect-0.3.12.dist-info/RECORD
