Metadata-Version: 2.1
Name: soft-collect
Version: 0.3.12
Summary: Soft-Collect
Home-page: https://github.com/unj-inovacao/soft-collect
License: MIT
Keywords: oracle,sqlserver
Author: Luccas Quadros
Author-email: luccas.quadros@softplan.com.br
Requires-Python: >=3.7.1,<4.0.0
Classifier: License :: OSI Approved :: MIT License
Classifier: Programming Language :: Python :: 3
Classifier: Programming Language :: Python :: 3.8
Requires-Dist: click (>=7.1.2,<8.0.0)
Requires-Dist: cx_Oracle (>=8.0.0,<9.0.0)
Requires-Dist: dynaconf (>=3.0.0,<4.0.0)
Requires-Dist: httpx (>=0.17.0,<0.18.0)
Requires-Dist: pandas (>=1.2.1,<2.0.0)
Requires-Dist: psycopg2-binary (==2.9.3)
Requires-Dist: pyodbc (>=4.0.30,<5.0.0)
Requires-Dist: rich (>=3.0.0,<4.0.0)
Requires-Dist: tqdm (>=4.59.0,<5.0.0)
Requires-Dist: tucuxi (>=0.1.2,<0.2.0)
Project-URL: Repository, https://github.com/unj-inovacao/soft-collect
